lily_assistant/__init__.py
lily_assistant/config.py
lily_assistant/checkers/__init__.py
lily_assistant/checkers/commit_message.py
lily_assistant/checkers/repo.py
lily_assistant/checkers/structure.py
lily_assistant/cli/__init__.py
lily_assistant/cli/base.makefile
lily_assistant/cli/checkers.py
lily_assistant/cli/cli.py
lily_assistant/cli/copier.py
lily_assistant/cli/logger.py
lily_assistant/cli/hooks/commit-msg
lily_assistant/cli/hooks/pre-commit
lily_assistant/repo/__init__.py
lily_assistant/repo/repo.py
lily_assistant/repo/version.py
lily_assistant-1.2.6.data/data/README.md
lily_assistant-1.2.6.data/data/base.makefile
lily_assistant-1.2.6.data/data/commit-msg
lily_assistant-1.2.6.data/data/config.json
lily_assistant-1.2.6.data/data/pre-commit
lily_assistant-1.2.6.data/data/requirements.txt
tests/__init__.py
tests/test_config.py
tests/test_checkers/__init__.py
tests/test_checkers/test_commit_message.py
tests/test_checkers/test_repo.py
tests/test_checkers/test_structure.py
tests/test_cli/__init__.py
tests/test_cli/test_cli.py
tests/test_cli/test_copier.py
tests/test_repo/__init__.py
tests/test_repo/test_repo.py
tests/test_repo/test_version.py
lily_assistant-1.2.6.dist-info/METADATA
lily_assistant-1.2.6.dist-info/WHEEL
lily_assistant-1.2.6.dist-info/entry_points.txt
lily_assistant-1.2.6.dist-info/top_level.txt
lily_assistant-1.2.6.dist-info/RECORD
