Metadata-Version: 2.1
Name: lily-assistant
Version: 1.2.6
Summary: Lily compatible code quality checking tool
Home-page: https://github.com/cosphere-org/lily-assistant.git
Author: CoSphere Team
Author-email: contact@cosphere.org
License: UNKNOWN
Keywords: lily
Platform: UNKNOWN
Requires-Dist: Click
Requires-Dist: pytest (>=4.3.1)
Requires-Dist: pytest-cov (>=2.6.1)
Requires-Dist: flake8 (<4.0,>=3.5.0)
Requires-Dist: pep8-naming (<1.0,>=0.7.0)
Requires-Dist: flake8-docstrings (<2.0,>=1.3.0)
Requires-Dist: pytest-randomly (==3.0.0)
